aioIP2Proxy.py
aioIP2Proxy-1.1.1.dist-info/LICENSE
aioIP2Proxy-1.1.1.dist-info/METADATA
aioIP2Proxy-1.1.1.dist-info/WHEEL
aioIP2Proxy-1.1.1.dist-info/top_level.txt
aioIP2Proxy-1.1.1.dist-info/RECORD
