Metadata-Version: 2.1
Name: aioIP2Proxy
Version: 1.1.1
Summary: Python API for IP2Proxy database. It can be used to query an IP address if it was being used as open proxy, web proxy, VPN anonymizer and TOR exits.
Home-page: https://github.com/sunset-developer/aioIP2Proxy
Author: sunset-developer
Author-email: aidanstewart@sunsetdeveloper.com
License: UNKNOWN
Platform: UNKNOWN
Classifier: Development Status :: 5 - Production/Stable
Classifier: Intended Audience :: Developers
Classifier: Topic :: Software Development :: Libraries :: Python Modules
Classifier: License :: OSI Approved :: MIT License
Classifier: Operating System :: OS Independent
